Metadata-Version: 2.1
Name: jk-jsoncfghelper2
Version: 0.2019.10.29
Summary: This python module contains support classes for loading and verifying configuratios. It is currently in alpha state as it is not yet clear how complete the implementation and how stable the API is. This modul might still undergo quite some rework.
Home-page: https://github.com/jkpubsrc/python-module-jk-jsoncfghelper2
Author: Jürgen Knauth
Author-email: pubsrc@binary-overflow.de
License: Apache 2.0
Download-URL: https://github.com/jkpubsrc/python-module-jk-jsoncfghelper2/tarball/0.2019.10.29
Keywords: configuration,json
Platform: UNKNOWN
Classifier: Development Status :: 3 - Alpha
Classifier: License :: OSI Approved :: Apache Software License
